ai_cogence_tools/__init__.py
ai_cogence_tools/server.py
ai_cogence_tools-1.1.0.dist-info/licenses/LICENSE
ai_cogence_tools-1.1.0.dist-info/METADATA
ai_cogence_tools-1.1.0.dist-info/WHEEL
ai_cogence_tools-1.1.0.dist-info/entry_points.txt
ai_cogence_tools-1.1.0.dist-info/top_level.txt
ai_cogence_tools-1.1.0.dist-info/RECORD
