Metadata-Version: 2.4
Name: ai-cogence-tools
Version: 1.1.0
Summary: MCP Tools for AI Cogence - Expose AI capabilities via Model Context Protocol
Author-email: AI Cogence Team <info@cogence.ai>
License: MIT
Project-URL: Homepage, https://www.cogence.ai
Project-URL: Documentation, https://github.com/ai-cogence/mcp-tools
Project-URL: Repository, https://github.com/ai-cogence/mcp-tools
Project-URL: Issues, https://github.com/ai-cogence/mcp-tools/issues
Keywords: mcp,ai,rag,tools,model-context-protocol
Classifier: Development Status :: 4 - Beta
Classifier: Intended Audience :: Developers
Classifier: License :: OSI Approved :: MIT License
Classifier: Programming Language :: Python :: 3
Classifier: Programming Language :: Python :: 3.10
Classifier: Programming Language :: Python :: 3.11
Classifier: Programming Language :: Python :: 3.12
Requires-Python: >=3.10
License-File: LICENSE
Requires-Dist: mcp>=1.16.0
Requires-Dist: python-dotenv>=1.0.0
Requires-Dist: psycopg[binary]>=3.2.9
Requires-Dist: psycopg-pool>=3.2.6
Requires-Dist: langchain-postgres>=0.0.15
Requires-Dist: langchain-openai>=0.3.28
Requires-Dist: langgraph
Requires-Dist: langgraph-checkpoint-postgres
Requires-Dist: openai>=1.98.0
Requires-Dist: httpx>=0.28.1
Dynamic: license-file
